pyxll_pycharm/__init__.py
pyxll_pycharm/resources/debug.png
pyxll_pycharm/resources/ribbon.xml
pyxll_pycharm-0.2.1.dist-info/LICENSE.md
pyxll_pycharm-0.2.1.dist-info/METADATA
pyxll_pycharm-0.2.1.dist-info/WHEEL
pyxll_pycharm-0.2.1.dist-info/entry_points.txt
pyxll_pycharm-0.2.1.dist-info/top_level.txt
pyxll_pycharm-0.2.1.dist-info/RECORD
