Metadata-Version: 2.1
Name: pyxll-pycharm
Version: 0.2.1
Summary: Adds PyCharm debugging support to PyXLL.
Home-page: UNKNOWN
License: UNKNOWN
Project-URL: Source, https://github.com/pyxll/pyxll-pycharm
Project-URL: Tracker, https://github.com/pyxll/pyxll-pycharm/issues
Platform: UNKNOWN
Classifier: Programming Language :: Python
Classifier: License :: OSI Approved :: MIT License
Classifier: Operating System :: Microsoft :: Windows
License-File: LICENSE.md
Requires-Dist: pyxll (>=5.0.0)
Requires-Dist: pydevd-pycharm
